[
  {
    "id": "CLI-001",
    "nom": "Dr Elena Ramirez",
    "historiqueCommandes": ["CMD-001", "CMD-002"]
  },
  {
    "id": "CLI-002",
    "nom": "Prof. Lucas Moretti",
    "historiqueCommandes": ["CMD-003"]
  },
  {
    "id": "CLI-003",
    "nom": "Dr Hana Watanabe",
    "historiqueCommandes": ["CMD-002", "CMD-005"]
  },
  {
    "id": "CLI-004",
    "nom": "Dr Samuel Thompson",
    "historiqueCommandes": ["CMD-004"]
  },
  {
    "id": "CLI-005",
    "nom": "Dr Aisha Ahmed",
    "historiqueCommandes": []
  }
]
