[
  {
    "id": "PORT-001",
    "nom": "Puerto Ayora",
    "coordonnees": {
      "latitude": -0.74,
      "longitude": -90.31
    },
    "ile": "ILE-001",
    "capaciteHydravions": 2,
    "capaciteHydravionsMax": 3,
    "lockers": ["LOC-001", "LOC-002"],
    "nbLockersVides": 1
  },
  {
    "id": "PORT-002",
    "nom": "Puerto Villamil",
    "coordonnees": {
      "latitude": -0.95,
      "longitude": -91.01
    },
    "ile": "ILE-002",
    "capaciteHydravions": 1,
    "capaciteHydravionsMax": 2,
    "lockers": ["LOC-003", "LOC-004"],
    "nbLockersVides": 1
  },
  {
    "id": "PORT-003",
    "nom": "Puerto Baquerizo Moreno",
    "coordonnees": {
      "latitude": -0.9,
      "longitude": -89.6
    },
    "ile": "ILE-003",
    "capaciteHydravions": 3,
    "capaciteHydravionsMax": 4,
    "lockers": ["LOC-005", "LOC-006", "LOC-007"],
    "nbLockersVides": 2
  },
  {
    "id": "PORT-004",
    "nom": "Puerto Velasco Ibarra",
    "coordonnees": {
      "latitude": -1.25,
      "longitude": -90.75
    },
    "ile": "ILE-004",
    "capaciteHydravions": 2,
    "capaciteHydravionsMax": 3,
    "lockers": ["LOC-008", "LOC-009"],
    "nbLockersVides": 0
  },
  {
    "id": "PORT-005",
    "nom": "Puerto Chino",
    "coordonnees": {
      "latitude": -0.92,
      "longitude": -89.45
    },
    "ile": "ILE-005",
    "capaciteHydravions": 1,
    "capaciteHydravionsMax": 2,
    "lockers": ["LOC-010"],
    "nbLockersVides": 1
  },
  {
    "id": "PORT-003",
    "nom": "Puerto Egas",
    "coordonnees": {
      "latitude": -0.27,
      "longitude": -91.13
    },
    "ile": "ILE-004",
    "capaciteHydravions": 4,
    "capaciteHydravionsMax": 5,
    "lockers": ["LOC-011", "LOC-012", "LOC-013", "LOC-014"],
    "nbLockersVides": 3
  }
]
